core_aws/__init__.py
core_aws/py.typed
core_aws/cdc/__init__.py
core_aws/cdc/targets/__init__.py
core_aws/cdc/targets/kinesis.py
core_aws/cdc/targets/sns.py
core_aws/cdc/targets/sqs.py
core_aws/ciphers/__init__.py
core_aws/ciphers/kms_cipher.py
core_aws/etls/__init__.py
core_aws/etls/base.py
core_aws/etls/bucket_based.py
core_aws/etls/sqs_based.py
core_aws/services/__init__.py
core_aws/services/base.py
core_aws/services/cloud_formation/__init__.py
core_aws/services/cloud_formation/client.py
core_aws/services/dynamo/__init__.py
core_aws/services/dynamo/client.py
core_aws/services/ecs/__init__.py
core_aws/services/ecs/client.py
core_aws/services/kinesis/__init__.py
core_aws/services/kinesis/client.py
core_aws/services/lambdas/__init__.py
core_aws/services/lambdas/decorators.py
core_aws/services/lambdas/events/__init__.py
core_aws/services/lambdas/events/base.py
core_aws/services/lambdas/events/kinesis_stream.py
core_aws/services/lambdas/events/sns_topic.py
core_aws/services/lambdas/events/sqs_queue.py
core_aws/services/s3/__init__.py
core_aws/services/s3/client.py
core_aws/services/sns/__init__.py
core_aws/services/sns/client.py
core_aws/services/sqs/__init__.py
core_aws/services/sqs/client.py
core_aws/services/ssm/__init__.py
core_aws/services/ssm/client.py
core_aws/tests/__init__.py
core_aws/tests/base.py
core_aws/tests/samples/__init__.py
core_aws/tests/samples/cloud_formation.py
core_aws/tests/samples/lambdas.py
core_aws/typing/__init__.py
core_aws/typing/cognito/__init__.py
core_aws/typing/cognito/identity.py
core_aws/typing/lambdas/__init__.py
core_aws/typing/lambdas/context.py
core_aws/typing/lambdas/events.py
core_aws/typing/mobile/__init__.py
core_aws/typing/mobile/client.py
core_aws/typing/ssm/__init__.py
core_aws/typing/ssm/parameter.py
core_aws-2.0.0.dist-info/licenses/LICENSE
core_aws-2.0.0.dist-info/METADATA
core_aws-2.0.0.dist-info/WHEEL
core_aws-2.0.0.dist-info/top_level.txt
core_aws-2.0.0.dist-info/RECORD
