Metadata-Version: 2.4
Name: core-aws
Version: 2.0.0
Summary: This project/library contains common elements related to AWS services...
Author-email: Alejandro Cora González <alek.cora.glez@gmail.com>
Maintainer: Alejandro Cora González
License-Expression: MIT
Project-URL: Homepage, https://gitlab.com/bytecode-solutions/core/core-aws
Project-URL: Repository, https://gitlab.com/bytecode-solutions/core/core-aws
Project-URL: Documentation, https://core-aws.readthedocs.io/en/latest/
Project-URL: Issues, https://gitlab.com/bytecode-solutions/core/core-aws/-/issues
Project-URL: Changelog, https://gitlab.com/bytecode-solutions/core/core-aws/-/blob/master/CHANGELOG.md
Classifier: Intended Audience :: Developers
Classifier: Development Status :: 5 - Production/Stable
Classifier: Topic :: Software Development :: Libraries :: Python Modules
Classifier: Topic :: Utilities
Classifier: Programming Language :: Python :: 3
Classifier: Programming Language :: Python :: 3 :: Only
Classifier: Programming Language :: Python :: 3.9
Classifier: Programming Language :: Python :: 3.10
Classifier: Programming Language :: Python :: 3.11
Classifier: Programming Language :: Python :: 3.12
Classifier: Programming Language :: Python :: 3.13
Requires-Python: >=3.9
License-File: LICENSE
Requires-Dist: aws-encryption-sdk>=4.0.0
Requires-Dist: boto3>=1.35.63
Requires-Dist: botocore>=1.35.63
Requires-Dist: core-ciphers>=1.2.1
Requires-Dist: core-etl>=3.0.0
Requires-Dist: core-mixins>=2.2.0
Requires-Dist: core-tests>=2.0.3
Provides-Extra: all
Requires-Dist: core-cdc>=2.0.1; extra == "all"
Provides-Extra: dev
Requires-Dist: core-dev-tools>=1.0.1; extra == "dev"
Requires-Dist: boto3-stubs>=1.35.0; extra == "dev"
Provides-Extra: core-cdc
Requires-Dist: core-cdc>=2.0.1; extra == "core-cdc"
Provides-Extra: tests
Requires-Dist: core-cdc[mongo]>=2.0.1; extra == "tests"
Requires-Dist: core-cdc[mysql]>=2.0.1; extra == "tests"
Dynamic: license-file
